signals/__init__.py
signals/fourparamsfit/__init__.py
signals/fourparamsfit/utils/__init__.py
signals/fourparamsfit/utils/curve_fit/__init__.py
signals/fourparamsfit/utils/curve_fit/four_params_dose_response.py
signals_fourparamsfit-0.0.2.dist-info/METADATA
signals_fourparamsfit-0.0.2.dist-info/WHEEL
signals_fourparamsfit-0.0.2.dist-info/top_level.txt
signals_fourparamsfit-0.0.2.dist-info/zip-safe
signals_fourparamsfit-0.0.2.dist-info/RECORD
