Metadata-Version: 2.1
Name: signals_fourparamsfit
Version: 0.0.2
Summary: Example package description
Author: signals
License: BSD 3-Clause License
Keywords: example,setuptools
Classifier: License :: OSI Approved :: BSD License
Classifier: Programming Language :: Python :: 3.10
Provides-Extra: dev
Requires-Dist: pytest ; extra == 'dev'
Requires-Dist: matplotlib ; extra == 'dev'
Provides-Extra: note
Requires-Dist: jupyter ; extra == 'note'
